pytest_kustomize/__init__.py
pytest_kustomize/plugin.py
pytest_kustomize/resource.py
pytest_kustomize-1.3.1.dist-info/METADATA
pytest_kustomize-1.3.1.dist-info/WHEEL
pytest_kustomize-1.3.1.dist-info/entry_points.txt
pytest_kustomize-1.3.1.dist-info/RECORD
