Metadata-Version: 2.4
Name: pytest_kustomize
Version: 1.3.1
Summary: Parse and validate kustomize output
Project-URL: repository, https://github.com/ZeitOnline/pytest_kustomize
Author-email: DIE ZEIT <engineering@zeit.de>
License: BSD-3-Clause
Requires-Python: >=3.7
Requires-Dist: pyyaml
Provides-Extra: jq
Requires-Dist: jq>=1.8.0; extra == 'jq'
